{
  "cod": "200",
  "message": 0,
  "cnt": 4,
  "list": [
    {
      "dt": 1710698400,
      "main": {
        "temp": 276.37,
        "feels_like": 272.65,
        "temp_min": 275.74,
        "temp_max": 276.37,
        "pressure": 996,
        "sea_level": 996,
        "grnd_level": 928,
        "humidity": 90,
        "temp_kf": 0.63
      },
      "weather": [
        {
          "id": 500,
          "main": "Rain",
          "description": "light rain",
          "icon": "10d"
        }
      ],
      "clouds": {
        "all": 98
      },
      "wind": {
        "speed": 4.29,
        "deg": 292,
        "gust": 9.05
      },
      "visibility": 3884,
      "pop": 1,
      "rain": {
        "3h": 1.38
      },
      "sys": {
        "pod": "d"
      },
      "dt_txt": "2024-03-17 18:00:00"
    },
    {
      "dt": 1710709200,
      "main": {
        "temp": 276.16,
        "feels_like": 271.91,
        "temp_min": 275.9,
        "temp_max": 276.16,
        "pressure": 997,
        "sea_level": 997,
        "grnd_level": 929,
        "humidity": 75,
        "temp_kf": 0.26
      },
      "weather": [
        {
          "id": 600,
          "main": "Snow",
          "description": "light snow",
          "icon": "13d"
        }
      ],
      "clouds": {
        "all": 91
      },
      "wind": {
        "speed": 5.18,
        "deg": 280,
        "gust": 10.02
      },
      "visibility": 10000,
      "pop": 0.83,
      "snow": {
        "3h": 0.54
      },
      "sys": {
        "pod": "d"
      },
      "dt_txt": "2024-03-17 21:00:00"
    },
    {
      "dt": 1710720000,
      "main": {
        "temp": 272.39,
        "feels_like": 268.15,
        "temp_min": 272.39,
        "temp_max": 272.39,
        "pressure": 1000,
        "sea_level": 1000,
        "grnd_level": 930,
        "humidity": 76,
        "temp_kf": 0
      },
      "weather": [
        {
          "id": 803,
          "main": "Clouds",
          "description": "broken clouds",
          "icon": "04n"
        }
      ],
      "clouds": {
        "all": 66
      },
      "wind": {
        "speed": 3.7,
        "deg": 270,
        "gust": 9.79
      },
      "visibility": 10000,
      "pop": 0.63,
      "sys": {
        "pod": "n"
      },
      "dt_txt": "2024-03-18 00:00:00"
    },
    {
      "dt": 1710730800,
      "main": {
        "temp": 271.21,
        "feels_like": 266.62,
        "temp_min": 271.21,
        "temp_max": 271.21,
        "pressure": 1001,
        "sea_level": 1001,
        "grnd_level": 931,
        "humidity": 81,
        "temp_kf": 0
      },
      "weather": [
        {
          "id": 803,
          "main": "Clouds",
          "description": "broken clouds",
          "icon": "04n"
        }
      ],
      "clouds": {
        "all": 52
      },
      "wind": {
        "speed": 3.82,
        "deg": 258,
        "gust": 9.88
      },
      "visibility": 10000,
      "pop": 0.06,
      "sys": {
        "pod": "n"
      },
      "dt_txt": "2024-03-18 03:00:00"
    }
  ],
  "city": {
    "id": 5236818,
    "name": "Hardwick",
    "coord": {
      "lat": 44.4348,
      "lon": -72.2723
    },
    "country": "US",
    "population": 1345,
    "timezone": -14400,
    "sunrise": 1710673017,
    "sunset": 1710716260
  }
}